yc_aws_wrapper/__about__.py
yc_aws_wrapper/__init__.py
yc_aws_wrapper/base.py
yc_aws_wrapper/exceptions.py
yc_aws_wrapper/kinesis/__init__.py
yc_aws_wrapper/s3/__init__.py
yc_aws_wrapper/sesv2/__init__.py
yc_aws_wrapper/sqs/__init__.py
yc_aws_wrapper-0.0.6.data/data/COPYRIGHT
yc_aws_wrapper-0.0.6.data/data/LICENSE
yc_aws_wrapper-0.0.6.dist-info/LICENSE
yc_aws_wrapper-0.0.6.dist-info/METADATA
yc_aws_wrapper-0.0.6.dist-info/WHEEL
yc_aws_wrapper-0.0.6.dist-info/top_level.txt
yc_aws_wrapper-0.0.6.dist-info/RECORD
