Metadata-Version: 2.1
Name: yc-aws-wrapper
Version: 0.0.6
Summary: yc-aws-wrapper.
Home-page: https://github.com/mcode-cc/python-yandex-cloud-sdk-wrapper/
Author: MCode GmbH
Author-email: python-yandex-cloud-sdk-wrapper@mcode.cc
License: GNU AFFERO GENERAL PUBLIC LICENSE Version 3, 29 June 2007
Project-URL: Bug Tracker, https://github.com/mcode-cc/python-yandex-cloud-sdk-wrapper/issues
Keywords: Wrapper for yandex cloud services
Platform: Any
Classifier: License :: OSI Approved :: GNU General Public License v3 (GPLv3)
Classifier: Development Status :: 1 - Planning
Classifier: Environment :: No Input/Output (Daemon)
Classifier: Environment :: Console
Classifier: Intended Audience :: Developers
Classifier: Operating System :: OS Independent
Classifier: Programming Language :: Python :: 3.8
Classifier: Programming Language :: Python :: Implementation :: CPython
Classifier: Programming Language :: Python :: Implementation :: PyPy
Classifier: Topic :: Internet
Classifier: Topic :: Communications
Classifier: Topic :: Database
Classifier: Topic :: Software Development :: Libraries
Classifier: Topic :: Software Development :: Libraries :: Application Frameworks
Classifier: Topic :: System :: Networking
License-File: LICENSE
Requires-Dist: boto3==1.27.1
Requires-Dist: botocore==1.30.1
